joinly/ai.py
joinly/join.py
llm_joinly-0.1.0.dist-info/METADATA
llm_joinly-0.1.0.dist-info/WHEEL
llm_joinly-0.1.0.dist-info/top_level.txt
llm_joinly-0.1.0.dist-info/RECORD
