Metadata-Version: 2.1
Name: llm-joinly
Version: 0.1.0
Summary: Join two lists with the use of LLMs
Author-email: Rich Whitcomb <richwhitjr@gmail.com>
Project-URL: Repository, https://github.com/richwhitjr/joinly
Project-URL: Documentation, https://richwhitjr.github.io/joinly/
Keywords: python
Classifier: Intended Audience :: Developers
Classifier: Programming Language :: Python
Classifier: Programming Language :: Python :: 3.11
Classifier: Programming Language :: Python :: 3.12
Classifier: Programming Language :: Python :: 3.13
Classifier: Topic :: Software Development :: Libraries :: Python Modules
Requires-Python: >=3.11
Requires-Dist: numpy>=1.14.3
Requires-Dist: openai>=1.58.0
Requires-Dist: tqdm>=4
